closure_tree/__init__.py
closure_tree/__version__.py
closure_tree/fields.py
closure_tree/migrations.py
closure_tree/models.py
closure_tree-0.1.0.dist-info/DESCRIPTION.rst
closure_tree-0.1.0.dist-info/METADATA
closure_tree-0.1.0.dist-info/RECORD
closure_tree-0.1.0.dist-info/WHEEL
closure_tree-0.1.0.dist-info/metadata.json
closure_tree-0.1.0.dist-info/top_level.txt
