Metadata-Version: 2.0
Name: closure-tree
Version: 0.1.0
Summary: A Closure based Tree model for Django.
Home-page: https://github.com/funkybob/closure_tree
Author: Curtis Maloney
Author-email: curtis@tinbrain.net
License: MIT
Platform: UNKNOWN
Classifier: License :: OSI Approved :: MIT License
Classifier: Programming Language :: Python
Classifier: Programming Language :: Python :: 3
Classifier: Programming Language :: Python :: 3.3
Classifier: Programming Language :: Python :: 3.4
Classifier: Programming Language :: Python :: 3.5
Classifier: Programming Language :: Python :: 3.6
Classifier: Programming Language :: Python :: Implementation :: CPython
Classifier: Programming Language :: Python :: Implementation :: PyPy
Requires-Dist: django
